<annotation><folder>train</folder><filename>447_jpg.rf.fcb355912b343f3240adf49156faf7bb.jpg</filename><path>./NUEVO_TRAIN/train\447_jpg.rf.fcb355912b343f3240adf49156faf7bb.jpg</path><source><database>roboflow.com</database></source><size><width>640</width><height>640</height><depth>3</depth></size><segmented>0</segmented><object><name>Maleza</name><pose>Unspecified</pose><truncated>0</truncated><difficult>0</difficult><occluded>0</occluded><bndbox><xmin>561</xmin><ymin>494</ymin><xmax>640</xmax><ymax>636</ymax></bndbox></object><object><name>Mosca</name><pose>Unspecified</pose><truncated>0</truncated><difficult>0</difficult><occluded>0</occluded><bndbox><xmin>307</xmin><ymin>247</ymin><xmax>318</xmax><ymax>265</ymax></bndbox></object><object><name>Maleza</name><pose>Unspecified</pose><truncated>0</truncated><difficult>0</difficult><occluded>0</occluded><bndbox><xmin>235</xmin><ymin>278</ymin><xmax>316</xmax><ymax>344</ymax></bndbox></object><object><name>Mosca</name><pose>Unspecified</pose><truncated>0</truncated><difficult>0</difficult><occluded>0</occluded><bndbox><xmin>289</xmin><ymin>256</ymin><xmax>308</xmax><ymax>275</ymax></bndbox></object><object><name>Mosca</name><pose>Unspecified</pose><truncated>0</truncated><difficult>0</difficult><occluded>0</occluded><bndbox><xmin>433</xmin><ymin>95</ymin><xmax>456</xmax><ymax>122</ymax></bndbox></object><object><name>Mosca</name><pose>Unspecified</pose><truncated>0</truncated><difficult>0</difficult><occluded>0</occluded><bndbox><xmin>395</xmin><ymin>323</ymin><xmax>418</xmax><ymax>341</ymax></bndbox></object></annotation>